context_info/__init__.py
context_info/tools/__init__.py
context_info/tools/context_info_tool.py
context_info/tools/utils.py
context_info/yamls/context_info_tool.yaml
tests/__init__.py
tests/test_context_info_tool.py
context_info_flow-0.0.1.dist-info/METADATA
context_info_flow-0.0.1.dist-info/WHEEL
context_info_flow-0.0.1.dist-info/entry_points.txt
context_info_flow-0.0.1.dist-info/top_level.txt
context_info_flow-0.0.1.dist-info/RECORD
