Metadata-Version: 2.1
Name: context_info_flow
Version: 0.0.1
Summary: This is including context information for LLM response
